{"code":200,"message":"成功","flag":true,"data":{"simCounts":[{"exerID":null,"title":null,"courseID":null,"catID":null,"optNum":null,"a":null,"b":null,"c":null,"d":null,"e":null,"f":null,"g":null,"h":null,"rightKey":null,"keyType":"单选题","analyze":null,"matRef":null,"diffCoeff":null,"freqCoeff":null,"exerType":null,"source":null,"isValid":null,"isMultiExer":null,"multiExerID":null,"isHtmlTag":null,"pracTimesAmount":null,"correctTimesAmount":null,"accuracyAmount":null,"reviewExerGroupID":null,"exerGroupId":null,"subTitle":null,"econtent":null,"jcontent":null,"agencyId":null,"isAudit":null,"adminId":null,"auditId":null,"auditTime":null,"createTime":null,"sourceExerId":null,"scoreRules":null,"scoreLess":null,"newKeyType":1,"isUnorderedMate":null,"isMaterial":null,"wrongSource":null,"score":null,"typeName":null,"isFinishs":0,"accuracy":null,"progressPercentage":null,"questionNumber":null,"questionAllNumber":null,"starCount":0,"sourceType":null,"collectionType":null,"cstId":null,"userKey":null,"wrongSum":null,"myCollectionld":null,"linkName":null,"simNum":55,"simScore":110.0,"answerTypeId":null,"exerNum":55,"prname":null},{"exerID":null,"title":null,"courseID":null,"catID":null,"optNum":null,"a":null,"b":null,"c":null,"d":null,"e":null,"f":null,"g":null,"h":null,"rightKey":null,"keyType":"问答题","analyze":null,"matRef":null,"diffCoeff":null,"freqCoeff":null,"exerType":null,"source":null,"isValid":null,"isMultiExer":null,"multiExerID":null,"isHtmlTag":null,"pracTimesAmount":null,"correctTimesAmount":null,"accuracyAmount":null,"reviewExerGroupID":null,"exerGroupId":null,"subTitle":null,"econtent":null,"jcontent":null,"agencyId":null,"isAudit":null,"adminId":null,"auditId":null,"auditTime":null,"createTime":null,"sourceExerId":null,"scoreRules":null,"scoreLess":null,"newKeyType":3,"isUnorderedMate":null,"isMaterial":null,"wrongSource":null,"score":null,"typeName":null,"isFinishs":0,"accuracy":null,"progressPercentage":null,"questionNumber":null,"questionAllNumber":null,"starCount":0,"sourceType":null,"collectionType":null,"cstId":null,"userKey":null,"wrongSum":null,"myCollectionld":null,"linkName":null,"simNum":2,"simScore":40.0,"answerTypeId":null,"exerNum":2,"prname":null}],"simExamStore":{"simID":60223,"examName":"2025年成考专升本英语-历年真题","courseID":"H012001","examDate":null,"totalScore":100.0,"passScore":0,"exerNum":57,"zone":null,"simType":"历年真题","examTime":150,"memo":null,"isVaild":1,"getScoreCondition":null,"sequence":0,"scoringMethod":1,"simExamCount":null,"startTime":null,"endTime":null,"authentication":0,"verifyCode":null,"exerSortType":1,"createTime":"2026-01-22T08:14:54.000+00:00","agencyId":0,"topicOrder":null,"isSelectExam":false,"isSample":0,"sampleNum":"","srId":null,"typeName":null,"mark":0.0,"isExamination":0,"catalogName":null,"doRecordNum":0,"cstId":12705,"title":null,"sampleNumJson":null,"isFinish":null,"isCollection":null,"score":0.0,"openStartDate":"","openEndDate":"","doTimes":150,"doNum":-1,"sortType":null,"intro":null,"courseName":"成考专升本英语","lastPosition":-1,"specialProjectId":277481,"lastExam":null,"isOpen":null,"projectName":"2025年成考专升本英语-历年真题","myCollectionId":null,"collectionType":null,"isTrailers":1,"productId":0,"simRecordType":null,"expiredStatus":false,"realExerNum":57,"courseNo":null,"prname":null,"umcId":null}}}